vlmrl/core/__init__.py
vlmrl/core/eval.py
vlmrl/core/grpo.py
vlmrl/core/sampling.py
vlmrl/envs/__init__.py
vlmrl/envs/base.py
vlmrl/envs/env_creator.py
vlmrl/envs/nlvr2.py
vlmrl/envs/vision_caption.py
vlmrl/models/__init__.py
vlmrl/models/qwen3vl.py
vlmrl/utils/__init__.py
vlmrl/utils/checkpoint.py
vlmrl/utils/configs.py
vlmrl/utils/hf_to_jax.py
vlmrl/utils/sharding.py
vlmrl/utils/train_state.py
vlmrl/utils/vlm.py
vlmrl/utils/wandb.py
vlmrl-0.0.1.dist-info/licenses/LICENSE
vlmrl-0.0.1.dist-info/licenses/NOTICE
vlmrl-0.0.1.dist-info/METADATA
vlmrl-0.0.1.dist-info/WHEEL
vlmrl-0.0.1.dist-info/top_level.txt
vlmrl-0.0.1.dist-info/RECORD
