Metadata-Version: 2.4
Name: vlmrl
Version: 0.0.1
Summary: RL for Vision Language Models
Author: Surya Dantuluri
License: Apache-2.0
Project-URL: Repository, https://github.com/sdan/vlmrl
Keywords: reinforcement-learning,vision-language-models,jax
Classifier: Development Status :: 3 - Alpha
Classifier: License :: OSI Approved :: Apache Software License
Classifier: Programming Language :: Python :: 3.10
Requires-Python: >=3.10
License-File: LICENSE
License-File: NOTICE
Requires-Dist: numpy
Requires-Dist: absl-py
Requires-Dist: ml-collections
Requires-Dist: wandb
Requires-Dist: einops
Requires-Dist: jaxtyping
Requires-Dist: opt-einsum
Requires-Dist: transformers
Requires-Dist: torch
Requires-Dist: tqdm
Requires-Dist: jax[cuda12]==0.6.1
Requires-Dist: optax==0.2.5
Requires-Dist: flax==0.10.6
Requires-Dist: chex==0.1.89
Requires-Dist: datasets>=4.1.1
Dynamic: license-file
